Metadata-Version: 2.1
Name: PyGenphi
Version: 0.8.0
Summary: Standard Datasource of Quant Trading
Home-page: https://github.com/eigenphi/PyGenphi
Author: David
Author-email: david@eigenphi.com
License: MIT
Platform: UNKNOWN
Classifier: Environment :: Web Environment
Classifier: Intended Audience :: Developers
Classifier: Operating System :: OS Independent
Classifier: Topic :: Text Processing :: Indexing
Classifier: Topic :: Utilities
Classifier: Topic :: Internet
Classifier: Topic :: Software Development :: Libraries :: Python Modules
Classifier: Programming Language :: Python
Classifier: Programming Language :: Python :: 3
Classifier: Programming Language :: Python :: 3.6
